LICENSE.md
MANIFEST.in
README.md
setup.cfg
setup.py
version.py
shell_timeit/__init__.py
shell_timeit/_testit.py
shell_timeit/_timeit.py
shell_timeit.egg-info/PKG-INFO
shell_timeit.egg-info/SOURCES.txt
shell_timeit.egg-info/dependency_links.txt
shell_timeit.egg-info/entry_points.txt
shell_timeit.egg-info/requires.txt
shell_timeit.egg-info/top_level.txt
shell_timeit.egg-info/zip-safe